{"responses":{"201":{"description":"","content":{"application/json":{"schema":{"type":"object","properties":{"code":{"type":"integer"},"message":{"type":"string"},"data":{"type":"object","properties":{"function_id":{"type":"string"},"name":{"type":"string"},"trigger":{"type":"string"},"effect_type":{"type":"string"},"effect":{"type":"object","properties":{"commission":{"type":"object","properties":{"commission_type":{"type":"string"},"commission_value":{"type":"integer"}},"required":["commission_type","commission_value"]}},"required":["commission"]},"conditions":{"type":"array","items":{"type":"string"}},"circle_id":{"type":"string"},"circle_name":{"type":"string"},"created_at":{"type":"string"},"updated_at":{"type":"string"}},"required":["function_id","name","trigger","effect_type","effect","conditions","circle_id","circle_name","created_at","updated_at"]}},"required":["code","message","data"]},"example":{"code":201,"message":"Successfully created function.","data":{"function_id":"89873fa6-80bb-4610-9773-d030bd5386db","name":"CUSTOMER_PURCHASE_10","trigger":"purchase","effect_type":"generate_commission","effect":{"commission":{"commission_type":"percentage","commission_value":10}},"conditions":[],"circle_id":"9d8c7b6a-5e4f-4a3b-9c1d-2e3f4a5b6c99","circle_name":"Premium Partners","created_at":"2026-04-08T06:52:03.075Z","updated_at":"2026-04-08T06:52:03.075Z"}}}},"headers":{}},"404":{"description":"","content":{"application/json":{"schema":{"type":"object","properties":{"code":{"type":"integer"},"message":{"type":"string"}},"required":["code","message"]},"example":{"code":404,"message":"Circle 972ddd2d-ed49-4ca0-a196-d663b698de42 does not exist in program 930433e7-591c-4dda-a300-d3bfe17bd03d."}}}}}}